setup.py
tracker.py
test_package_avinav.egg-info/PKG-INFO
test_package_avinav.egg-info/SOURCES.txt
test_package_avinav.egg-info/dependency_links.txt
test_package_avinav.egg-info/top_level.txt