Metadata-Version: 2.1
Name: test-package-avinav
Version: 0.0.1
Summary: Security literacy test tracker
Author: Your Name
Classifier: Programming Language :: Python :: 3
